tgtlg/UserDynaConfig.py
tgtlg/__init__.py
tgtlg/__main__.py
tgtlg/helper_funcs/__init__.py
tgtlg/helper_funcs/admin_check.py
tgtlg/helper_funcs/cloneHelper.py
tgtlg/helper_funcs/copy_similar_file.py
tgtlg/helper_funcs/create_compressed_archive.py
tgtlg/helper_funcs/direct_link_generator.py
tgtlg/helper_funcs/display_progress.py
tgtlg/helper_funcs/download.py
tgtlg/helper_funcs/download_aria_p_n.py
tgtlg/helper_funcs/download_from_link.py
tgtlg/helper_funcs/exceptions.py
tgtlg/helper_funcs/extract_link_from_message.py
tgtlg/helper_funcs/help_Nekmo_ffmpeg.py
tgtlg/helper_funcs/magnetic_link_regex.py
tgtlg/helper_funcs/real_debrid_extractor.py
tgtlg/helper_funcs/split_large_files.py
tgtlg/helper_funcs/upload_to_tg.py
tgtlg/helper_funcs/youtube_dl_button.py
tgtlg/helper_funcs/youtube_dl_extractor.py
tgtlg/helper_funcs/ytplaylist.py
tgtlg/plugins/__init__.py
tgtlg/plugins/call_back_button_handler.py
tgtlg/plugins/choose_rclone_config.py
tgtlg/plugins/custom_thumbnail.py
tgtlg/plugins/incoming_message_fn.py
tgtlg/plugins/new_join_fn.py
tgtlg/plugins/rclone_size.py
tgtlg/plugins/status_message_fn.py
tgtlg-1.3.4.data/scripts/extract
tgtlg-1.3.4.dist-info/LICENSE
tgtlg-1.3.4.dist-info/METADATA
tgtlg-1.3.4.dist-info/WHEEL
tgtlg-1.3.4.dist-info/entry_points.txt
tgtlg-1.3.4.dist-info/top_level.txt
tgtlg-1.3.4.dist-info/RECORD
