Metadata-Version: 2.1
Name: tgtlg
Version: 1.3.4
Summary: A Telegram Torrent (and youtube-dl) Leecher based on Pyrogram.
Home-page: https://github.com/reaitten/tgtlg
Author: reaitten
Author-email: wsy0xf2u8@relay.firefox.com
License: UNKNOWN
Project-URL: Bug Tracker, https://github.com/reaitten/tgtlg/issues
Platform: UNKNOWN
Classifier: Programming Language :: Python :: 3.8
Classifier: Operating System :: POSIX :: Linux
Classifier: Development Status :: 5 - Production/Stable
Requires-Python: >=3.8.2
License-File: LICENSE
Requires-Dist: wheel
Requires-Dist: rust
Requires-Dist: aiohttp
Requires-Dist: aria2p (==0.9.1)
Requires-Dist: hachoir
Requires-Dist: Pillow
Requires-Dist: Pyrogram
Requires-Dist: tgcrypto
Requires-Dist: youtube-dl
Requires-Dist: hurry.filesize
Requires-Dist: python-telegram-bot
Requires-Dist: python-dotenv
Requires-Dist: beautifulsoup4 (<4.8.10,>=4.8.2)
Requires-Dist: requests
Requires-Dist: messages
Requires-Dist: js2py
